{
  "active": true,
  "connections": {
    "Schedule Trigger": {
      "main": [
        [
          {
            "node": "Google Sheets1",
            "type": "main",
            "index": 0
          },
          {
            "node": "Southern",
            "type": "main",
            "index": 0
          },
          {
            "node": "Northern",
            "type": "main",
            "index": 0
          },
          {
            "node": "Central",
            "type": "main",
            "index": 0
          },
          {
            "node": "Eastern",
            "type": "main",
            "index": 0
          },
          {
            "node": "Google Sheets3",
            "type": "main",
            "index": 0
          }
        ]
      ]
    },
    "Postgres": {
      "main": [
        [
          {
            "node": "Google Sheets",
            "type": "main",
            "index": 0
          }
        ]
      ]
    },
    "Google Sheets1": {
      "main": [
        [
          {
            "node": "Postgres",
            "type": "main",
            "index": 0
          }
        ]
      ]
    },
    "Postgres1": {
      "main": [
        [
          {
            "node": "Google Sheets2",
            "type": "main",
            "index": 0
          }
        ]
      ]
    },
    "Google Sheets3": {
      "main": [
        [
          {
            "node": "Postgres1",
            "type": "main",
            "index": 0
          }
        ]
      ]
    }
  },
  "createdAt": "2023-03-24T07:20:20.573Z",
  "id": "50",
  "name": "[JIUN] [HOST COMMUNITY] Car Age >= 10 Years Listings",
  "nodes": [
    {
      "parameters": {
        "rule": {
          "interval": [
            {
              "field": "weeks",
              "triggerAtDay": [
                1
              ],
              "triggerAtHour": 10
            }
          ]
        }
      },
      "id": "05216a37-0adf-42c8-8554-de0285338498",
      "name": "Schedule Trigger",
      "type": "n8n-nodes-base.scheduleTrigger",
      "typeVersion": 1,
      "position": [
        220,
        920
      ]
    },
    {
      "parameters": {
        "operation": "executeQuery",
        "query": "SET TIMEZONE = 'Asia/Kuala_Lumpur';\n\nselect distinct l.id, \nl.registration_no, \ncase when ll.city_id in (1) then 'KV'   \nwhen ll.city_id in (2,12) then 'PGM' when ll.city_id in (48) then 'PGI'\nwhen ll.city_id in (3,19,20,21) then 'KK'   when ll.city_id in (4) then 'JB' \nwhen ll.city_id in (5) then 'IP'   when ll.city_id in (47) then 'NS'\nwhen ll.city_id in (13) then 'LGK' \nwhen ll.city_id in (14) then 'PRLS'\nwhen ll.city_id in (15) then 'MLK'\nwhen ll.city_id in (16) then 'PHG'\nwhen ll.city_id in (17) then 'TRGN'\nwhen ll.city_id in (18) then 'KLT'\nwhen ll.city_id in (22,23) then 'KCH'\nelse 'Others' end as City,\nm.year,\nu.uuid, \nu.email,\ncase when b.listing_id is null then 'No' else 'Yes' end as future_bookings,\nTRUNC(cast(to_char(CURRENT_DATE, 'yyyy') AS NUMERIC) - m.year) as car_age\nfrom listings l \nleft join models m on m.id = l.model_id\nleft join listing_location ll on ll.listing_id = l.id\nleft join users u on u.id = l.user_id\nleft join \n\t(select distinct b.listing_id\n\tfrom bookings b \n\tleft join listing_location ll on ll.listing_id = b.listing_id\n\twhere 1=1\n\tand ll.country = 'Malaysia'\n\tand b.status in ('accepted', 'waiting_for_inspection', 'start_driving', 'return_car')\n\tand b.request_end_at >= NOW())b\n\ton b.listing_id = l.id\nwhere 1=1\nand l.status = 'approved'\nand l.deleted_at is null\nand ll.country = 'Malaysia'\ngroup by 1,2,3,4,5,6,7\nhaving TRUNC(cast(to_char(CURRENT_DATE, 'yyyy') AS NUMERIC) - m.year) >= 10",
        "options": {}
      },
      "id": "0214f9d3-721d-432d-bae7-f2a4879a9efa",
      "name": "Postgres",
      "type": "n8n-nodes-base.postgres",
      "typeVersion": 2.2,
      "position": [
        620,
        920
      ],
      "credentials": {
        "postgres": {
          "id": "8",
          "name": "Trevo DB"
        }
      }
    },
    {
      "parameters": {
        "operation": "appendOrUpdate",
        "documentId": {
          "__rl": true,
          "value": "1KPFMtyFmbAkc0KrvcdsubSU7Pri9JGK5mLhVviygsZs",
          "mode": "list",
          "cachedResultName": "Car Age >= 10 Years",
          "cachedResultUrl": "https://docs.google.com/spreadsheets/d/1KPFMtyFmbAkc0KrvcdsubSU7Pri9JGK5mLhVviygsZs/edit?usp=drivesdk"
        },
        "sheetName": {
          "__rl": true,
          "value": "gid=0",
          "mode": "list",
          "cachedResultName": "Sheet1",
          "cachedResultUrl": "https://docs.google.com/spreadsheets/d/1KPFMtyFmbAkc0KrvcdsubSU7Pri9JGK5mLhVviygsZs/edit#gid=0"
        },
        "columns": {
          "mappingMode": "autoMapInputData",
          "value": {},
          "matchingColumns": [
            "id"
          ],
          "schema": [
            {
              "id": "id",
              "displayName": "id",
              "required": false,
              "defaultMatch": true,
              "display": true,
              "type": "string",
              "canBeUsedToMatch": true,
              "removed": false
            },
            {
              "id": "registration_no",
              "displayName": "registration_no",
              "required": false,
              "defaultMatch": false,
              "display": true,
              "type": "string",
              "canBeUsedToMatch": true
            },
            {
              "id": "city",
              "displayName": "city",
              "required": false,
              "defaultMatch": false,
              "display": true,
              "type": "string",
              "canBeUsedToMatch": true
            },
            {
              "id": "year",
              "displayName": "year",
              "required": false,
              "defaultMatch": false,
              "display": true,
              "type": "string",
              "canBeUsedToMatch": true
            },
            {
              "id": "car_age",
              "displayName": "car_age",
              "required": false,
              "defaultMatch": false,
              "display": true,
              "type": "string",
              "canBeUsedToMatch": true
            }
          ]
        },
        "options": {
          "cellFormat": "USER_ENTERED"
        }
      },
      "id": "a3e1a9b9-8577-4a64-929b-f92db168257f",
      "name": "Google Sheets",
      "type": "n8n-nodes-base.googleSheets",
      "typeVersion": 4,
      "position": [
        780,
        920
      ],
      "credentials": {
        "googleSheetsOAuth2Api": {
          "id": "19",
          "name": "Google Sheet - Jiun's Account"
        }
      }
    },
    {
      "parameters": {
        "operation": "clear",
        "documentId": {
          "__rl": true,
          "value": "1KPFMtyFmbAkc0KrvcdsubSU7Pri9JGK5mLhVviygsZs",
          "mode": "list",
          "cachedResultName": "Car Age >= 10 Years",
          "cachedResultUrl": "https://docs.google.com/spreadsheets/d/1KPFMtyFmbAkc0KrvcdsubSU7Pri9JGK5mLhVviygsZs/edit?usp=drivesdk"
        },
        "sheetName": {
          "__rl": true,
          "value": "gid=0",
          "mode": "list",
          "cachedResultName": "Sheet1",
          "cachedResultUrl": "https://docs.google.com/spreadsheets/d/1KPFMtyFmbAkc0KrvcdsubSU7Pri9JGK5mLhVviygsZs/edit#gid=0"
        },
        "clear": "specificRange",
        "range": "A2:Z"
      },
      "id": "441451c2-afdd-4828-9b39-c502e2c5260e",
      "name": "Google Sheets1",
      "type": "n8n-nodes-base.googleSheets",
      "typeVersion": 4,
      "position": [
        460,
        920
      ],
      "credentials": {
        "googleSheetsOAuth2Api": {
          "id": "19",
          "name": "Google Sheet - Jiun's Account"
        }
      }
    },
    {
      "parameters": {
        "spaceId": "spaces/AAAAuAnAjjE",
        "messageUi": {
          "text": "=[URGENT] Reminder to check this sheet for listings >= 10 years\n\nLink: https://docs.google.com/spreadsheets/d/1KPFMtyFmbAkc0KrvcdsubSU7Pri9JGK5mLhVviygsZs/edit?usp=sharing"
        },
        "additionalFields": {}
      },
      "id": "f55d91b0-232f-475f-ae51-8aeaeb2413e9",
      "name": "Central",
      "type": "n8n-nodes-base.googleChat",
      "typeVersion": 1,
      "position": [
        460,
        400
      ],
      "credentials": {
        "googleApi": {
          "id": "26",
          "name": "Google Chat [Pat]"
        }
      }
    },
    {
      "parameters": {
        "spaceId": "spaces/AAAAuAnAjjE",
        "messageUi": {
          "text": "=[URGENT] Reminder to check this sheet for listings >= 10 years\n\nLink: https://docs.google.com/spreadsheets/d/1KPFMtyFmbAkc0KrvcdsubSU7Pri9JGK5mLhVviygsZs/edit?usp=sharing"
        },
        "additionalFields": {}
      },
      "id": "5297bf29-edf7-4971-9fac-643ace931a9b",
      "name": "Central3",
      "type": "n8n-nodes-base.googleChat",
      "typeVersion": 1,
      "position": [
        2120,
        1060
      ],
      "credentials": {
        "googleApi": {
          "id": "26",
          "name": "Google Chat [Pat]"
        }
      }
    },
    {
      "parameters": {
        "spaceId": "spaces/AAAAgvG0aiA",
        "messageUi": {
          "text": "=[URGENT] Reminder to check this sheet for listings >= 10 years\n\nLink: https://docs.google.com/spreadsheets/d/1KPFMtyFmbAkc0KrvcdsubSU7Pri9JGK5mLhVviygsZs/edit?usp=sharing"
        },
        "additionalFields": {}
      },
      "id": "156e3390-0f87-419f-8bf8-ea3be05d162e",
      "name": "Eastern",
      "type": "n8n-nodes-base.googleChat",
      "typeVersion": 1,
      "position": [
        460,
        240
      ],
      "credentials": {
        "googleApi": {
          "id": "26",
          "name": "Google Chat [Pat]"
        }
      }
    },
    {
      "parameters": {
        "spaceId": "spaces/AAAAty2-MzA",
        "messageUi": {
          "text": "=[URGENT] Reminder to check this sheet for listings >= 10 years\n\nLink: https://docs.google.com/spreadsheets/d/1KPFMtyFmbAkc0KrvcdsubSU7Pri9JGK5mLhVviygsZs/edit?usp=sharing"
        },
        "additionalFields": {}
      },
      "id": "ca9128da-650e-434b-a4dd-72f34f05b086",
      "name": "Northern",
      "type": "n8n-nodes-base.googleChat",
      "typeVersion": 1,
      "position": [
        460,
        580
      ],
      "credentials": {
        "googleApi": {
          "id": "26",
          "name": "Google Chat [Pat]"
        }
      }
    },
    {
      "parameters": {
        "spaceId": "spaces/AAAAOZfALAA",
        "messageUi": {
          "text": "=[URGENT] Reminder to check this sheet for listings >= 10 years\n\nLink: https://docs.google.com/spreadsheets/d/1KPFMtyFmbAkc0KrvcdsubSU7Pri9JGK5mLhVviygsZs/edit?usp=sharing"
        },
        "additionalFields": {}
      },
      "id": "5c8b1502-b4f8-461a-a083-476419706ecb",
      "name": "Southern",
      "type": "n8n-nodes-base.googleChat",
      "typeVersion": 1,
      "position": [
        460,
        760
      ],
      "credentials": {
        "googleApi": {
          "id": "26",
          "name": "Google Chat [Pat]"
        }
      }
    },
    {
      "parameters": {
        "operation": "executeQuery",
        "query": "SET TIMEZONE = 'Asia/Kuala_Lumpur';\n\nselect distinct l.id, \nl.registration_no,\nconcat(u.first_name,' ',u.last_name)as host_name, \nu.phone_number, \nu.email,\ncase when ll.city_id in (1) then 'KV'   \nwhen ll.city_id in (2,12) then 'PGM' when ll.city_id in (48) then 'PGI'\nwhen ll.city_id in (3,19,20,21) then 'KK'   when ll.city_id in (4) then 'JB' \nwhen ll.city_id in (5) then 'IP'   when ll.city_id in (47) then 'NS'\nwhen ll.city_id in (13) then 'LGK' \nwhen ll.city_id in (14) then 'PRLS'\nwhen ll.city_id in (15) then 'MLK'\nwhen ll.city_id in (16) then 'PHG'\nwhen ll.city_id in (17) then 'TRGN'\nwhen ll.city_id in (18) then 'KLT'\nwhen ll.city_id in (22,23) then 'KCH'\nelse 'Others' end as City,\nm.year,\nA.clt, \nTRUNC(cast(to_char(CURRENT_DATE, 'yyyy') AS NUMERIC) - m.year) as car_age, \nt.name as SC_tag\nfrom listings l \nleft join models m on m.id = l.model_id\nleft join listing_location ll on ll.listing_id = l.id\nleft join users u on u.id = l.user_id \n--\n    left join \n    (select distinct b.listing_id,\n    max(b.created_at) as clt\n    from bookings b \n    where b.status = 'completed'\n    group by 1)A\n    on A.listing_id = l.id\n--\n    left join\n    (select distinct l.id, \n\tt.name\n\tfrom listings l \n\tLEFT JOIN tag_taggables tt ON tt.taggable_id = l.id AND tt.taggable = 'listings'\n\tleft JOIN tags t ON t.id = tt.tag_id AND t.name LIKE 'SC%'\n\twhere t.name is not null)t\n\ton t.id = l.id\nwhere 1=1\nand (l.status = 'rejected' or l.deleted_at is not null)\nand ll.country = 'Malaysia'\ngroup by 1,2,3,4,5,6,7,8,9,10\nhaving TRUNC(cast(to_char(CURRENT_DATE, 'yyyy') AS NUMERIC) - m.year) >= 10\n\n",
        "options": {}
      },
      "id": "1a74a9a1-570f-43ad-b0b0-4aecc4809fcc",
      "name": "Postgres1",
      "type": "n8n-nodes-base.postgres",
      "typeVersion": 2.2,
      "position": [
        620,
        1100
      ],
      "credentials": {
        "postgres": {
          "id": "8",
          "name": "Trevo DB"
        }
      }
    },
    {
      "parameters": {
        "operation": "appendOrUpdate",
        "documentId": {
          "__rl": true,
          "value": "1KPFMtyFmbAkc0KrvcdsubSU7Pri9JGK5mLhVviygsZs",
          "mode": "list",
          "cachedResultName": "Car Age >= 10 Years",
          "cachedResultUrl": "https://docs.google.com/spreadsheets/d/1KPFMtyFmbAkc0KrvcdsubSU7Pri9JGK5mLhVviygsZs/edit?usp=drivesdk"
        },
        "sheetName": {
          "__rl": true,
          "value": 1332145169,
          "mode": "list",
          "cachedResultName": "Rejected",
          "cachedResultUrl": "https://docs.google.com/spreadsheets/d/1KPFMtyFmbAkc0KrvcdsubSU7Pri9JGK5mLhVviygsZs/edit#gid=1332145169"
        },
        "columns": {
          "mappingMode": "autoMapInputData",
          "value": {},
          "matchingColumns": [
            "id"
          ],
          "schema": [
            {
              "id": "id",
              "displayName": "id",
              "required": false,
              "defaultMatch": true,
              "display": true,
              "type": "string",
              "canBeUsedToMatch": true
            },
            {
              "id": "registration_no",
              "displayName": "registration_no",
              "required": false,
              "defaultMatch": false,
              "display": true,
              "type": "string",
              "canBeUsedToMatch": true
            },
            {
              "id": "host_name",
              "displayName": "host_name",
              "required": false,
              "defaultMatch": false,
              "display": true,
              "type": "string",
              "canBeUsedToMatch": true
            },
            {
              "id": "phone_number",
              "displayName": "phone_number",
              "required": false,
              "defaultMatch": false,
              "display": true,
              "type": "string",
              "canBeUsedToMatch": true
            },
            {
              "id": "email",
              "displayName": "email",
              "required": false,
              "defaultMatch": false,
              "display": true,
              "type": "string",
              "canBeUsedToMatch": true
            },
            {
              "id": "city",
              "displayName": "city",
              "required": false,
              "defaultMatch": false,
              "display": true,
              "type": "string",
              "canBeUsedToMatch": true
            },
            {
              "id": "year",
              "displayName": "year",
              "required": false,
              "defaultMatch": false,
              "display": true,
              "type": "string",
              "canBeUsedToMatch": true
            },
            {
              "id": "clt",
              "displayName": "clt",
              "required": false,
              "defaultMatch": false,
              "display": true,
              "type": "string",
              "canBeUsedToMatch": true
            },
            {
              "id": "car_age",
              "displayName": "car_age",
              "required": false,
              "defaultMatch": false,
              "display": true,
              "type": "string",
              "canBeUsedToMatch": true
            },
            {
              "id": "sc_tag",
              "displayName": "sc_tag",
              "required": false,
              "defaultMatch": false,
              "display": true,
              "type": "string",
              "canBeUsedToMatch": true
            }
          ]
        },
        "options": {
          "cellFormat": "USER_ENTERED"
        }
      },
      "id": "62a40a0e-9674-4aae-ae51-b8c3296e0a48",
      "name": "Google Sheets2",
      "type": "n8n-nodes-base.googleSheets",
      "typeVersion": 4,
      "position": [
        780,
        1100
      ],
      "credentials": {
        "googleSheetsOAuth2Api": {
          "id": "19",
          "name": "Google Sheet - Jiun's Account"
        }
      }
    },
    {
      "parameters": {
        "operation": "clear",
        "documentId": {
          "__rl": true,
          "value": "1KPFMtyFmbAkc0KrvcdsubSU7Pri9JGK5mLhVviygsZs",
          "mode": "list",
          "cachedResultName": "Car Age >= 10 Years",
          "cachedResultUrl": "https://docs.google.com/spreadsheets/d/1KPFMtyFmbAkc0KrvcdsubSU7Pri9JGK5mLhVviygsZs/edit?usp=drivesdk"
        },
        "sheetName": {
          "__rl": true,
          "value": 1332145169,
          "mode": "list",
          "cachedResultName": "Rejected",
          "cachedResultUrl": "https://docs.google.com/spreadsheets/d/1KPFMtyFmbAkc0KrvcdsubSU7Pri9JGK5mLhVviygsZs/edit#gid=1332145169"
        },
        "clear": "specificRange",
        "range": "A2:Z"
      },
      "id": "262500fc-725d-4561-b5b3-90de96b395bf",
      "name": "Google Sheets3",
      "type": "n8n-nodes-base.googleSheets",
      "typeVersion": 4,
      "position": [
        460,
        1100
      ],
      "credentials": {
        "googleSheetsOAuth2Api": {
          "id": "19",
          "name": "Google Sheet - Jiun's Account"
        }
      }
    }
  ],
  "pinData": {},
  "settings": {
    "saveManualExecutions": false,
    "callerPolicy": "workflowsFromSameOwner",
    "errorWorkflow": "11"
  },
  "staticData": {
    "node:Schedule Trigger": {
      "recurrencyRules": []
    },
    "global": {
      "oldListingIds": [
        "IU3PTGAL",
        "YK1MFFU2",
        "RHYGVEZO",
        "7HWK9OY6",
        "QJO4YHET",
        "34RQGYOE",
        "2OWXRD86",
        "F4HB8RUB",
        "UZD0DCTR",
        "32I8HYP5",
        "I9G4NLKU",
        "0DY9LAGI",
        "BMPY1Y1C",
        "CJW3OTE1",
        "W07UVNJI",
        "P46LGN1X",
        "T67SQ8MP",
        "19VK3JTA",
        "KOZ8HXLN",
        "EOJQ2QBV",
        "0XTOHK8V",
        "6Z1AUJM2",
        "GKTKVLCV",
        "M69FHIB5",
        "AE76NKR2",
        "IU7GBSCO",
        "QG78R969",
        "LSYGV9FP",
        "1HM7J5QH",
        "0OXHT6YG",
        "TLI5NUGG",
        "BWNRQJHL",
        "SM5K4RC0",
        "XNXUHW5J",
        "2GZ4SWHO",
        "WU6YJMB5",
        "FWLYEP3V",
        "LKB6V6KY",
        "FGYYLQUC",
        "1F5TSJXS",
        "5V99G0A1",
        "HZ3TLVWR",
        "0W20BQA2",
        "FA16B8KH",
        "HHU0NC4Y",
        "CHTZ1PS2",
        "G7PX0LVZ",
        "H7ZUJYJB",
        "30UNSJCL",
        "UGJ69IC2",
        "DODVO76S",
        "O5UR8A6K",
        "X9HDHBZ2",
        "WRO8LV7Z",
        "8M8VSVQM",
        "C024W4ZM",
        "F36U6A8T",
        "BJWB8822",
        "0UNPQL9E",
        "FTWIDWES",
        "K7F6AZJ7",
        "KBPOY5AN",
        "RIBWSGZN",
        "FEX4MRKY",
        "3JTJTL7B",
        "X3NPQ2XJ",
        "A1X41OQU",
        "YU4H24JZ",
        "L7TDWMFG",
        "OE0Q12GW",
        "XL7Q2OO6",
        "PJMM8106",
        "T1QBVGLM",
        "L5P7SGEI",
        "OS1EJJWD",
        "5D3S4AY5",
        "DNOLBF3X",
        "WFM0MLFH",
        "365S1JJP",
        "BGUZ3TZD",
        "Y2197B7R",
        "D8W8SRW5",
        "LZIAW07W",
        "9MN9IOX2",
        "SQMEB5OI",
        "8Y3ZH4R7",
        "7KLAKCDP",
        "A3DRUR8D",
        "080ZF29S",
        "K8CU2VMW",
        "WSISVNQP",
        "OWZQEI5H",
        "QFTZTYK1",
        "K61SVJH5",
        "X7A5JIMG",
        "414GRYRK",
        "9ZT2TX3Y",
        "AN0N5USX",
        "DVOWEM6O",
        "WA83CVBR",
        "JBUNQJMI",
        "10N507HM",
        "HOYB0GNT",
        "P5Z3WCM1",
        "C240IAGC",
        "LHCXO4IF",
        "Y371IMN9",
        "TQU2RBF5",
        "AVACDU65",
        "SIP6ZDHE",
        "S9G11TPX",
        "W6Z3CO9O",
        "O0V9NMU7",
        "LSKO5NYX",
        "7W9PDE7J",
        "F1E0CE02",
        "WLWAJISE",
        "GU0A908C",
        "M9JN0MH5",
        "JQMLVX76",
        "A2BJNRN2",
        "B8RWIV8V",
        "GP71WHSE",
        "HRQK9NC9",
        "24ET8NXH",
        "PLOJHE19",
        "80B772O3",
        "1ILX522U",
        "A21G0LE0",
        "CYDHVSX4",
        "Q2K6AIMT",
        "FSW185KG",
        "B90TDUH7",
        "QOJWY5S0",
        "JABDNUY9",
        "RPJNEDUQ",
        "4ZLEB8ST",
        "O7DN00E8",
        "7H7F035U",
        "XKLI2JBA",
        "G34HZ8M6",
        "1OMHRN01",
        "93EJ6HUD",
        "NHFIF46H",
        "1KUUKJGT",
        "5GH84SPO",
        "44SESDN2",
        "9UU9N22C",
        "KE25LSNO",
        "IA0VJNBT",
        "S6OP8OHI",
        "W2UO4D5K",
        "6NGPICMA",
        "5VO7P2U3",
        "E37F74T3",
        "TH16Q60F",
        "QRL6R3NT",
        "Z6FL3FAB",
        "IE0OHH91",
        "AFYESDYA",
        "YALL0YOT",
        "ELPOGCIN",
        "MN9EB7CO",
        "T2V5F1PB",
        "ZPWUCJ6T",
        "BJ7S07D9",
        "N0VYHWON",
        "P95ATVVS",
        "HYU80NA2",
        "NK9LTORS",
        "SBGQ1LZ6",
        "6Z2REGTK",
        "4V8CODK0",
        "LSETPDYT",
        "VP7V33WO",
        "AOCWEN9L",
        "O3G0PH7O",
        "HW9A9R3W",
        "JHW9BD9O",
        "MJ6V2PFZ",
        "M26DJMFB",
        "KQ8ZPHN6",
        "N9FHAXDX",
        "DARNXD1W",
        "YCGH6YZU",
        "44NCUX3O",
        "MMBJVNBK",
        "BP51GSLA",
        "CXYCA20U",
        "KYDPOCLJ",
        "06EZBHXN",
        "WIQ3FWP0",
        "L7KRTABZ",
        "Z4K2A9H9",
        "3MV793Q9",
        "23K6KU8I",
        "5PVJ68D0",
        "S63W0NRL",
        "ZFIDS0US",
        "QTY06FF3",
        "AYF03TU5",
        "YND75D4Q",
        "DV5BP4IM",
        "GSVHTCZ8",
        "6UD63N8X",
        "XJJD4QAB",
        "O1U8HB3E",
        "GC1FZSOS",
        "H2YSRBW3",
        "TGN43848",
        "IRY7BX2W",
        "SNK3QGAC",
        "1DREBW1H",
        "DCXZMXD6",
        "KIY3OSX9",
        "LRYPW5XW",
        "X7C5O34O",
        "PYLLRGYC",
        "4RNTLN73",
        "7R2H9ZM7",
        "5WDHHNQE",
        "JLYX8ZS2",
        "9PYJ31ZO",
        "P9KYCRJI",
        "QR8EA12O",
        "3XEREJJV",
        "GZHZ2F2M",
        "MH08T83L",
        "R74GNC70",
        "OOI2Q4GQ",
        "0M9LZKCZ",
        "2EPN3G61",
        "EEBZS918",
        "YT6QOO6Y",
        "2NS6VTDU",
        "JNY9X5TQ",
        "XCWYSFQ8",
        "AQMVNJ5W",
        "EQKTDMWN",
        "ZZVOL61E",
        "5P2XOQLY",
        "Y3MJY62O",
        "KTZGSAJK",
        "S2RMSS1D",
        "JMO6NCUV",
        "TNLYQS9Q",
        "CWH00D5A",
        "FWTQY97V",
        "I6H75LUA",
        "6BFNYE7W",
        "SMKU1N1I",
        "2IJCVVR6",
        "O5RCTY91",
        "RS4WZCBO",
        "VOQ07AKH",
        "AQIO5UNL",
        "J0BNDFQD",
        "HPDSLJVF",
        "ORC1MOT4",
        "65NE9XY0",
        "6FVSIY6I",
        "APX73JAS",
        "EM7O0IUX",
        "PRW1P6NN",
        "3BDSF6Z0",
        "1L75KN4Q",
        "77JTBWBL",
        "DFYTHI0O",
        "JAMXBK1E",
        "PL0GWL82",
        "7SDZ6U3S",
        "68FQQX5M",
        "S107CSLY",
        "JDTDYPCW",
        "JZ4REYV8",
        "BMY0N26B",
        "9FLL7HN5",
        "4HZ224TP",
        "W75DL2O7",
        "QPY4YKVB",
        "C0JQ31EN",
        "9LQ3JKT9",
        "FVBV56LZ",
        "ZA70V7GG",
        "Z1O82TL8",
        "719Z5NFJ",
        "IS8S4MPL",
        "4JD2U9GJ",
        "9TF3Y91Q",
        "WVQ807L6",
        "3AQ08M4K",
        "WBTTSTSK",
        "9YGHVAEM",
        "OPGZSEXA",
        "RXM4HBW4",
        "WE59VT1N",
        "BXCJ5USJ",
        "I3I7SNS4",
        "LMH45VG8",
        "NV6KJJKF",
        "067L8ZY7",
        "D3A7KKM2",
        "6RL31XGH",
        "Q5SEDFWE",
        "IWSYJW1D",
        "0SS394CC",
        "D4A66N4C",
        "EYNK8YZ3",
        "0U081KP1",
        "BZ863L3T",
        "8O7MG2NZ",
        "QT81DA9I",
        "56PY4ZZ5",
        "T9O2TNBO",
        "C6SN063G",
        "URHA0A32",
        "2A37115X",
        "VFKC8O2A",
        "LRPSKAS3",
        "HOPD8O09",
        "OG2N933L",
        "6UIJD1AO",
        "H2EJAEGU",
        "4ZK0FZAY",
        "NLVPPA7B",
        "1ZWOIOMF",
        "HRZNQN8B",
        "XOO4IFWN",
        "YLFTGDJZ",
        "ZO1LU0EO",
        "8V8VD9SX",
        "LOD34OX2",
        "RHFVN5Z8",
        "OIOXGI3D",
        "2T4PSIGM",
        "9JUY6CN4",
        "DZAVFM8F",
        "MYIZNK2Z",
        "NDFKVHD2",
        "QO9COXAZ",
        "YIOJJGX4",
        "SKBAM3LI",
        "LWAHALU1",
        "J028NGPK",
        "5TP5NI2A",
        "HE7B8VYQ",
        "JIU3FGHN",
        "AS3J5P5Q",
        "LIR5BZ7F",
        "8U3VDFL4",
        "UGVVZR2T",
        "IF9MM8G1",
        "S4XQY72P",
        "W0B83GLC",
        "U0PNU83S",
        "D4Q38M5Z",
        "ZI6YI1DK",
        "JF33HMMC",
        "5LM90KDH",
        "USSB1ZWR",
        "DYV8GZOA",
        "E12OAY2V",
        "JL7JXG7J",
        "MD5A3Q0Q",
        "ZQ9IRMVK",
        "9BQ2ALDT",
        "1WHB41EB",
        "WBGF71UQ",
        "WX3E1HTX",
        "QESR1V3J",
        "CIYDQYSX",
        "5HU8HPSD",
        "CUONRG7C",
        "HFW1YO9T",
        "PRU27FZX",
        "4OYADYHH",
        "KB1LTEBU",
        "4V4033J6",
        "F9VNRD5J",
        "28SZLCWP",
        "2EMLEP7N",
        "9BNSIW64",
        "HVT6FC0R",
        "N4KVC8K9",
        "UUH8UIVE",
        "GPQ6IOJ4",
        "X8PEMY69",
        "VLUUXTEF",
        "8TOSZXDQ",
        "7H1644NM",
        "RU2EKT9A",
        "YEVYI7UK",
        "ZG5R6S84",
        "T9DFOO97",
        "P38SXJW6",
        "XY5BGGXV",
        "0NL73VP8",
        "NXMHNLBP",
        "YD87RSNJ",
        "K6SHWEFX",
        "0UEZ1H1S",
        "5KRQ3PA0",
        "I7G35HH0",
        "3ZWSH22A",
        "W7MOBZDD",
        "KBBOSGKU",
        "KZXMQ3X2",
        "LM4J5V6S",
        "L850CAYM",
        "J3KFZWZD",
        "NHOYXX84",
        "QGNGUFMF",
        "OAX2FN32",
        "27U2Z1I8",
        "49DP287G",
        "FZ4UPQMS",
        "PYM42IBC",
        "5Q8SONAX",
        "FXEUFX9N",
        "NQ10RSL5",
        "E4L9T5NT",
        "8R1XX4CN",
        "0PC1JVG2",
        "1EUOKPZD",
        "WVZ29ZA0",
        "LOK91NC8",
        "NVG4XHSA",
        "K4K20N81",
        "R1MPZXN2",
        "P7XTADB7",
        "QOHP2YBK",
        "8N3C8UNW",
        "0HZZJ1ZM",
        "TKGG1IHE",
        "4IRZTQ2I",
        "HAIL6TB3",
        "QONSUZ2U",
        "0D1PPTE2",
        "0EU69ZUV",
        "19I036ZU",
        "2RXVV1RS",
        "3MXGL8YQ",
        "3W4WY050",
        "43LPLLJU",
        "5D734RZC",
        "5EQKM1GA",
        "5FIA9H02",
        "7AVWJ756",
        "8980Y3KP",
        "8BU6GHWH",
        "9D9HKT6Z",
        "AIIALLPP",
        "AL1XKZZS",
        "AR8JCDCQ",
        "BR9D8V06",
        "DALB9K8Q",
        "DV2Z9V5F",
        "ECLV4IOM",
        "F60Z0B25",
        "FB1JF6FS",
        "FTRL2GXK",
        "GY8722GR",
        "HJFW544M",
        "HZEERJHC",
        "HZLIC0PZ",
        "IORV2T8K",
        "JBQTSYQD",
        "JP7HU0Z3",
        "K3V2Y17M",
        "KSFWF4FX",
        "LFVKGF3O",
        "LSM5BX4E",
        "MQ61BEUD",
        "ON666LLD",
        "PA0Z0U6I",
        "PC6LLAAK",
        "PYCZ8FUD",
        "R06ET4R2",
        "SPNZOJ3E",
        "THJIADKI",
        "UA4B68DD",
        "UQ0O9AWA",
        "VX7BC2BH",
        "VZME9SLD",
        "XBKATZCQ",
        "YEDILLQE",
        "Z30EDRV5",
        "ZUPSSM65",
        35624,
        35622,
        35623,
        35621,
        35620,
        35619,
        35618,
        35617,
        35612,
        35613,
        35614,
        35615,
        35616,
        35610,
        35611,
        35609,
        35608,
        35607,
        35600,
        35601,
        35602,
        35603,
        35605,
        35606,
        35599,
        35598,
        35597,
        35596,
        35595,
        35594,
        35593,
        35590,
        35591,
        35592,
        35589,
        35587,
        35588,
        35586,
        35585,
        35584,
        35583,
        35580,
        35581,
        35582,
        35579,
        35578,
        35577,
        35576,
        35574,
        35575,
        35573,
        35572,
        35571,
        35570,
        35569,
        35568,
        35564,
        35565,
        35566,
        35567,
        35563,
        35562,
        35561,
        35560,
        35559,
        35558,
        35557,
        35556,
        35555,
        35554,
        35553,
        35552,
        35551,
        35550,
        35549,
        35547,
        35546,
        35545,
        35544,
        35543,
        35542,
        35541,
        35540,
        35539,
        35537,
        35538,
        35536,
        35535,
        35534,
        35533,
        35532,
        35531,
        35528,
        35529,
        35527,
        35526,
        35525,
        35524,
        35523,
        35521,
        35522,
        35510,
        35511,
        35512,
        35513,
        35514,
        35515,
        35516,
        35517,
        35518,
        35508,
        35507,
        35505,
        35504,
        35503,
        35502,
        35499,
        35500,
        35501,
        35498,
        35497,
        35496,
        35494,
        35493,
        35492,
        35491,
        35490,
        35488,
        35489,
        35485,
        35486,
        35487,
        35483,
        35484,
        35482,
        35480,
        35481,
        35479,
        35478,
        35475,
        35476,
        35477,
        35474,
        35473,
        35472,
        35471,
        35470,
        35469,
        35468,
        35467,
        35466,
        35463,
        35464,
        35462,
        35461,
        35460,
        35459,
        35458,
        35457,
        35456,
        35455,
        35454,
        35450,
        35451,
        35452,
        35453,
        35449,
        35448,
        35446,
        35437,
        35438,
        35439,
        35440,
        35441,
        35442,
        35443,
        35444,
        35445,
        35436,
        35435,
        35434,
        35433,
        35432,
        35427,
        35428,
        35429,
        35430,
        35426,
        35424,
        35423,
        35422,
        35421,
        35414,
        35415,
        35416,
        35417,
        35418,
        35419,
        35420,
        35412,
        35408,
        35409,
        35410,
        35411,
        35405,
        35404,
        35403,
        35402,
        35401,
        35400,
        35399,
        35398,
        35386,
        35387,
        35388,
        35389,
        35390,
        35391,
        35392,
        35393,
        35394,
        35395,
        35397,
        35384,
        35382,
        35383,
        35380,
        35379,
        35377,
        35378,
        35376,
        35374,
        35375,
        35373,
        35363,
        35364,
        35365,
        35366,
        35367,
        35368,
        35369,
        35370,
        35371,
        35372,
        35362,
        35360,
        35357,
        35358,
        35359,
        35356,
        35355,
        35354,
        35352,
        35353,
        35351,
        35349,
        35348,
        35347,
        35346,
        35345,
        35344,
        35343,
        35342,
        35341,
        35340,
        35339,
        35338,
        35337,
        35336,
        35335,
        35334,
        35333,
        35332,
        35331,
        35330,
        35328,
        35329,
        35327,
        35326,
        35325,
        35324,
        35323,
        35321,
        35322,
        35320,
        35319,
        35317,
        35318,
        35316,
        35315,
        35313,
        35314,
        35311,
        35312,
        35310,
        35309,
        35308,
        35307,
        35306,
        35302,
        35303,
        35304,
        35301,
        35300,
        35299,
        35297,
        35296,
        35295,
        35293,
        35294,
        35292,
        35291,
        35290,
        35287,
        35288,
        35289,
        35285,
        35284,
        35281,
        35282,
        35283,
        35279,
        35278,
        35277,
        35276,
        35275,
        35265,
        35266,
        35268,
        35269,
        35270,
        35271,
        35272,
        35273,
        35274,
        35264,
        35263,
        35262,
        35261,
        35260,
        35259,
        35258,
        35257,
        35256,
        35255,
        35232,
        35233,
        35234,
        35235,
        35236,
        35237,
        35238,
        35239,
        35240,
        35241,
        35242,
        35243,
        35244,
        35245,
        35246,
        35247,
        35248,
        35250,
        35251,
        35252,
        35253,
        35254,
        35231,
        35230,
        35229,
        35226,
        35227,
        35228,
        35224,
        35222,
        35223,
        35221,
        35220,
        35219,
        35217,
        35216,
        35209,
        35210,
        35211,
        35212,
        35213,
        35214,
        35215,
        35208,
        35207,
        35206,
        35205,
        35204,
        35201,
        35202,
        35203,
        35197,
        35198,
        35199,
        35200,
        35196,
        35195,
        35194,
        35193,
        35192,
        35191,
        35190,
        35189,
        35184,
        35185,
        35186,
        35187,
        35188,
        35183,
        35182,
        35181,
        35180,
        35179,
        35178,
        35176,
        35174,
        35175,
        35173,
        35172,
        35171,
        35170,
        35169,
        35168,
        35166,
        35165,
        35164,
        35163,
        35157,
        35159,
        35160,
        35161,
        35162,
        35155,
        35154,
        35153,
        35152,
        35150,
        35151,
        35145,
        35146,
        35147,
        35148,
        35144,
        35142,
        35143,
        35141,
        35134,
        35135,
        35136,
        35137,
        35139,
        35140,
        35133,
        35132,
        35131,
        35130,
        35129,
        35128,
        35127,
        35126,
        35125,
        35124,
        35123,
        35122,
        35121,
        35120,
        35119,
        35117,
        35118,
        35109,
        35110,
        35111,
        35112,
        35113,
        35114,
        35115,
        35116,
        35107,
        35108,
        35104,
        35105,
        35106,
        35103,
        35102,
        35101,
        35100,
        35099,
        35098,
        35097,
        35096,
        35093,
        35094,
        35095,
        35092,
        35091,
        35089,
        35090,
        35088,
        35087,
        35086,
        35085,
        35084,
        35083,
        35082,
        35081,
        35080,
        35077,
        35079,
        35076,
        35074,
        35075,
        35072,
        35070,
        35068,
        35069,
        35064,
        35066,
        35067,
        35061,
        35062,
        35060,
        35059,
        35058,
        35056,
        35057,
        35055,
        35054,
        35047,
        35048,
        35049,
        35050,
        35052,
        35053,
        35046,
        35045,
        35044,
        35043,
        35042,
        35041,
        35040,
        35039,
        35038,
        35037,
        35036,
        35035,
        35034,
        35033,
        35031,
        35030,
        35029,
        35028,
        35026,
        35025,
        35024,
        35018,
        35019,
        35020,
        35022,
        35023,
        35017,
        35016,
        35014,
        35013,
        35012,
        35011,
        35010,
        35008,
        35007,
        35006,
        35005,
        35004,
        35003,
        35002,
        34994,
        34995,
        34996,
        34997,
        34998,
        34999,
        35000,
        34993,
        34992,
        34991,
        34990,
        34989,
        34987,
        34988,
        34986,
        34985,
        34984,
        34983,
        34982,
        34980,
        34981,
        34979,
        34978,
        34977,
        34976,
        34975,
        34974,
        34973,
        34972,
        34971,
        34970,
        34962,
        34963,
        34964,
        34966,
        34967,
        34968,
        34969,
        34961,
        34960,
        34959,
        34958,
        34957,
        34956,
        34955,
        34953,
        34952,
        34951,
        34949,
        34948,
        34947,
        34946,
        34945,
        34942,
        34943,
        34944,
        34939,
        34940,
        34941,
        34938,
        34937,
        34936,
        34935,
        34934,
        34933,
        34932,
        34931,
        34930,
        34929,
        34928,
        34927,
        34926,
        34925,
        34924,
        34923,
        34920,
        34921,
        34922,
        34919,
        34918,
        34917,
        34915,
        34910,
        34911,
        34912,
        34913,
        34914,
        34909,
        34908,
        34904,
        34905,
        34906,
        34907,
        34903,
        34902,
        34901,
        34898,
        34900,
        34893,
        34894,
        34895,
        34896,
        34897,
        34892,
        34891,
        34890,
        34887,
        34888,
        34885,
        34886,
        34884,
        34883,
        34882,
        34881,
        34880,
        34879,
        34878,
        34874,
        34875,
        34876,
        34877,
        34873,
        34872,
        34871,
        34870,
        34869,
        34868,
        34867,
        34866,
        34865,
        34864,
        34863,
        34861,
        34862,
        34860,
        34858,
        34857,
        34856,
        34854,
        34852,
        34851,
        34849,
        34850,
        34847,
        34846,
        34845,
        34844,
        34843,
        34842,
        34841,
        34840,
        34839,
        34838,
        34837,
        34828,
        34829,
        34831,
        34832,
        34834,
        34836,
        34821,
        34822,
        34823,
        34824,
        34825,
        34826,
        34827,
        34820,
        34819,
        34813,
        34814,
        34815,
        34816,
        34817,
        34818,
        34812,
        34811,
        34809,
        34810,
        34807,
        34808,
        34806,
        34805,
        34804,
        34803,
        34802,
        34799,
        34800,
        34797,
        34798,
        34796,
        34795,
        34794,
        34793,
        34788,
        34790,
        34792,
        34786,
        34787,
        34784,
        34785,
        34783,
        34782,
        34781,
        34780,
        34777,
        34778,
        34779,
        34776,
        34775,
        34773,
        34774,
        34770,
        34771,
        34772,
        34756,
        34757,
        34758,
        34759,
        34760,
        34762,
        34763,
        34764,
        34765,
        34766,
        34767,
        34769,
        34755,
        34752,
        34753,
        34754,
        34751,
        34750,
        34749,
        34748,
        34747,
        34746,
        34745,
        34744,
        34743,
        34742,
        34735,
        34736,
        34737,
        34738,
        34739,
        34740,
        34741,
        34731,
        34732,
        34733,
        34734,
        34730,
        34729,
        34728,
        34727,
        34726,
        34721,
        34722,
        34723,
        34724,
        34725,
        34720,
        34719,
        34718,
        34716,
        34715,
        34711,
        34712,
        34713,
        34714,
        34710,
        34709,
        34708,
        34707,
        34706,
        34705,
        34704,
        34703,
        34702,
        34700,
        34701,
        34698,
        34697,
        34696,
        34695,
        34692,
        34690,
        34678,
        34680,
        34681,
        34682,
        34683,
        34686,
        34687,
        34688,
        34689,
        34676,
        34677,
        34674,
        34672,
        34673,
        34670,
        34671,
        34669,
        34668,
        34667,
        34666,
        34665,
        34664,
        34661,
        34663,
        34660,
        34657,
        34650,
        34651,
        34652,
        34653,
        34654,
        34655,
        34656,
        34649,
        34647,
        34648,
        34645,
        34646,
        34644,
        34643,
        34640,
        34641,
        34642,
        34639,
        34632,
        34633,
        34634,
        34635,
        34636,
        34637,
        34638,
        34631,
        34630,
        34629,
        34627,
        34626,
        34625,
        34620,
        34616,
        34617,
        34618,
        34619,
        34615,
        34614,
        34613,
        34612,
        34611,
        34603,
        34604,
        34605,
        34606,
        34607,
        34608,
        34609,
        34601,
        34600,
        34599,
        34598,
        34595,
        34596,
        34597,
        34594,
        34592,
        34593,
        34591,
        34589,
        34588,
        34576,
        34577,
        34578,
        34580,
        34581,
        34582,
        34583,
        34584,
        34585,
        34586,
        34587,
        34575,
        34574,
        34569,
        34570,
        34571,
        34572,
        34573,
        34568,
        34567,
        34566,
        34562,
        34564,
        34565,
        34561,
        34560,
        34559,
        34558,
        34557,
        34556,
        34555,
        34554,
        34553,
        34552,
        34551,
        34550,
        34549,
        34548,
        34546,
        34547,
        34545,
        34544,
        34543,
        34542,
        34541,
        34540,
        34539,
        34538,
        34537,
        34536,
        34535,
        34534,
        34533,
        34532,
        34531,
        34530,
        34529,
        34528,
        34527,
        34526,
        34525,
        34524,
        34523,
        34522,
        34521,
        34520,
        34519,
        34518,
        34517,
        34516,
        34515,
        34514,
        34513,
        34510,
        34511,
        34509,
        34508,
        34507,
        34504,
        34505,
        34506,
        34501,
        34502,
        34503,
        34500,
        34499,
        34495,
        34496,
        34497,
        34498,
        34494,
        34493,
        34492,
        34491,
        34490,
        34489,
        34487,
        34486,
        34485,
        34484,
        34483,
        34482,
        34480,
        34481,
        34477,
        34478,
        34479,
        34476,
        34475,
        34474,
        34472,
        34473,
        34471,
        34470,
        34469,
        34468,
        34465,
        34464,
        34461,
        34462,
        34463,
        34460,
        34459,
        34457,
        34458,
        34456,
        34455,
        34454,
        34452,
        34453,
        34450,
        34449,
        34444,
        34445,
        34446,
        34447,
        34448,
        34443,
        34442,
        34441,
        34440,
        34439,
        34438,
        34437,
        34436,
        34435,
        34434,
        34433,
        34432,
        34431,
        34430,
        34429,
        34428,
        34427,
        34426,
        34425,
        34424,
        34422,
        34421,
        34419,
        34420,
        34418,
        34417,
        34416,
        34415,
        34414,
        34411,
        34410,
        34409,
        34407,
        34406,
        34405,
        34404,
        34403,
        34398,
        34399,
        34400,
        34401,
        34402,
        34397,
        34396,
        34395,
        34394,
        34393,
        34392,
        34391,
        34387,
        34388,
        34389,
        34390,
        34383,
        34384,
        34385,
        34386,
        34382,
        34381,
        34379,
        34380,
        34378,
        34377,
        34376,
        34375,
        34374,
        34373,
        34372,
        34368,
        34369,
        34370,
        34371,
        34366,
        34367,
        34365,
        34364,
        34363,
        34361,
        34362,
        34360,
        34359,
        34358,
        34356,
        34357,
        34354,
        34353,
        34352,
        34351,
        34344,
        34345,
        34347,
        34348,
        34349,
        34350,
        34343,
        34342,
        34340,
        34339,
        34338,
        34337,
        34336,
        34335,
        34334,
        34330,
        34331,
        34332,
        34329,
        34328,
        34326,
        34327,
        34325,
        34324,
        34323,
        34321,
        34322,
        34320,
        34316,
        34317,
        34318,
        34319,
        34307,
        34308,
        34309,
        34310,
        34311,
        34312,
        34313,
        34314,
        34315,
        34306,
        34304,
        34303,
        34302,
        34301,
        34298,
        34299,
        34300,
        34295,
        34296,
        34297,
        34293,
        34292,
        34290,
        34291,
        34289,
        34288,
        34287,
        34285,
        34286,
        34284,
        34283,
        34282,
        34281,
        34280,
        34266,
        34267,
        34268,
        34269,
        34270,
        34271,
        34272,
        34273,
        34274,
        34275,
        34276,
        34277,
        34278,
        34279,
        34264,
        34265,
        34263,
        34262,
        34260,
        34257,
        34258,
        34256,
        34255,
        34254,
        34253,
        34252,
        "",
        "",
        "",
        "",
        "",
        "",
        "",
        "",
        "",
        "",
        "",
        "",
        "",
        "",
        "",
        "",
        "",
        "",
        "",
        "",
        "",
        "",
        "",
        "",
        "",
        "",
        "",
        "",
        "",
        "",
        "",
        "",
        "",
        "",
        "",
        "",
        "",
        "",
        "",
        "",
        "",
        "",
        "",
        "",
        "",
        "",
        "",
        "",
        "",
        "",
        "",
        "",
        "",
        "",
        "",
        "",
        "",
        "",
        "",
        "",
        "",
        "",
        "",
        "",
        "",
        "",
        "",
        "",
        "",
        "",
        "",
        "",
        "",
        "",
        "",
        "",
        "",
        "",
        "",
        "",
        "",
        "",
        "",
        "",
        "",
        "",
        "",
        "",
        "",
        34251,
        34245,
        34246,
        34247,
        34248,
        34249,
        34250,
        34244,
        34242,
        34243,
        34240,
        34241,
        34239,
        34238,
        34237,
        34235,
        34234,
        34232,
        34230,
        34229,
        34228,
        34227,
        34223,
        34224,
        34225,
        34226,
        34222,
        34221,
        34220,
        34216,
        34217,
        34218,
        34219,
        34215,
        34214,
        34213,
        34212,
        34211,
        34206,
        34207,
        34208,
        34209,
        34210,
        34204,
        34205,
        34203,
        34202,
        34200,
        34201,
        34199,
        34198,
        34197,
        34196,
        34195,
        34194,
        34193,
        34184,
        34185,
        34187,
        34189,
        34190,
        34191,
        34181,
        34182,
        34180,
        34176,
        34177,
        34178,
        34179,
        34175,
        34174,
        34173,
        34172,
        34169,
        34170,
        34171,
        34168,
        34165,
        34166,
        34167,
        34164,
        34163,
        34162,
        34161,
        34160,
        34159,
        34157,
        34158,
        34156,
        34153,
        34154,
        34152,
        34151,
        34150,
        34149,
        34145,
        34146,
        34147,
        34143,
        34142,
        34141,
        34140,
        34139,
        34136,
        34137,
        34138,
        34135,
        34133,
        34134,
        34132,
        34128,
        34129,
        34130,
        34131,
        34127,
        34125,
        34126,
        34124,
        34123,
        34121,
        34122,
        34118,
        34119,
        34120,
        34116,
        34113,
        34114,
        34115,
        34112,
        34110,
        34111,
        34109,
        34108,
        34107,
        34106,
        34105,
        34104,
        34103,
        34101,
        34102,
        34100,
        34099,
        34098,
        34097,
        34095,
        34096,
        34094,
        34093,
        34091,
        34090,
        34089,
        34088,
        34087,
        34086,
        34085,
        34083,
        34084,
        34082,
        34081,
        34080,
        34074,
        34075,
        34076,
        34077,
        34078,
        34079,
        34073,
        34070,
        34072,
        34069,
        34068,
        34067,
        34065,
        34066,
        34064,
        34063,
        34062,
        34061,
        34059,
        34060,
        34058,
        34057,
        34056,
        34055,
        34054,
        34053,
        34052,
        34051,
        34044,
        34045,
        34046,
        34047,
        34048,
        34049,
        34050,
        34043,
        34042,
        34041,
        34038,
        34039,
        34040,
        34033,
        34034,
        34035,
        34036,
        34037,
        34032,
        34031,
        34030,
        34029,
        34028,
        34027,
        34026,
        34024,
        34025,
        34023,
        34022,
        34019,
        34015,
        34016,
        34017,
        34018,
        34014,
        34012,
        34013,
        34011,
        34010,
        34009,
        34008,
        34007,
        34006,
        34005,
        34004,
        34003,
        34002,
        34001,
        33999,
        34000,
        33998,
        33997,
        33996,
        33995,
        33994,
        33993,
        33992,
        33991,
        33990,
        33989,
        33988,
        33987,
        33982,
        33983,
        33984,
        33985,
        33986,
        33979,
        33980,
        33981,
        33975,
        33976,
        33977,
        33978,
        33971,
        33972,
        33973,
        33974,
        33969,
        33970,
        33964,
        33965,
        33966,
        33967,
        33968,
        33963,
        33962,
        33961,
        33959,
        33958,
        33957,
        33955,
        33956,
        33954,
        33953,
        33952,
        33950,
        33951,
        33949,
        33948,
        33946,
        33947,
        33942,
        33943,
        33944,
        33945,
        33941,
        33940,
        33939,
        33936,
        33937,
        33938,
        33935,
        33934,
        33933,
        33932,
        33930,
        33931,
        33929,
        33928,
        33926,
        33927,
        33925,
        33924,
        33922,
        33923,
        33921,
        33919,
        33920,
        33918,
        33917,
        33916,
        33915,
        33912,
        33913,
        33914,
        33907,
        33910,
        33911,
        33862,
        33863,
        33864,
        33865,
        33866,
        33867,
        33868,
        33869,
        33870,
        33871,
        33872,
        33873,
        33874,
        33875,
        33876,
        33877,
        33878,
        33879,
        33880,
        33881,
        33882,
        33883,
        33884,
        33885,
        33886,
        33887,
        33888,
        33889,
        33890,
        33891,
        33892,
        33893,
        33894,
        33895,
        33896,
        33897,
        33898,
        33899,
        33900,
        33901,
        33902,
        33903,
        33904,
        33905,
        33906,
        27081,
        26314,
        24403
      ]
    }
  },
  "tags": [],
  "triggerCount": 1,
  "updatedAt": "2024-08-08T02:48:30.445Z",
  "versionId": "fde938d8-6162-4587-b5a0-c68b79d48fa1"
}